{
    "keep": {
        "days": true,
        "amount": 3
    },
    "auditLog": "D:\\Apps\\React_SMP Notice Board\\logs\\.8536d6af5df1052926ea982419ac796d956d8b31-audit.json",
    "files": [
        {
            "date": 1761578603955,
            "name": "D:\\Apps\\React_SMP Notice Board\\logs\\debug-2025-10-27.log",
            "hash": "db652e925249f2326cf304ae243385c285f044412a76220599d202981e670a4b"
        },
        {
            "date": 1761657738560,
            "name": "D:\\Apps\\React_SMP Notice Board\\logs\\debug-2025-10-28.log",
            "hash": "a2cfb26a68682852b5c6efd5b8a079c14adaa46ae773562e60591484a869249b"
        },
        {
            "date": 1761705896239,
            "name": "D:\\Apps\\React_SMP Notice Board\\logs\\debug-2025-10-29.log",
            "hash": "337366c606d2bc8dd66f0261433d417bbcdb710607979cec648c089990d04835"
        }
    ],
    "hashType": "sha256"
}